mcmc_samplers/__init__.py
mcmc_samplers/proposals/__init__.py
mcmc_samplers/proposals/gaussian_random_walk.py
mcmc_samplers/proposals/hamiltonian.py
mcmc_samplers/proposals/proposal.py
mcmc_samplers/samplers/__init__.py
mcmc_samplers/samplers/delayed_rejection.py
mcmc_samplers/samplers/hamiltonian.py
mcmc_samplers/samplers/sampler.py
mcmc_samplers/samples/__init__.py
mcmc_samplers/samples/hamiltonian.py
mcmc_samplers/samples/sample.py
mcmc_samplers/visualization/sample_visualizer.py
mcmc_samplers-0.0.3.dist-info/licenses/LICENSE
mcmc_samplers-0.0.3.dist-info/METADATA
mcmc_samplers-0.0.3.dist-info/WHEEL
mcmc_samplers-0.0.3.dist-info/top_level.txt
mcmc_samplers-0.0.3.dist-info/RECORD
