Metadata-Version: 2.4
Name: mcmc-samplers
Version: 0.0.3
Summary: A Python package for MCMC sampling.
Author-email: Nicholas Galioto <ngalioto@umich.edu>
License: GPLv3
Project-URL: Homepage, https://github.com/ngalioto/mcmc-samplers
Keywords: Markov chain Monte Carlo,MCMC,sampling,Metropolis-Hastings,delayed rejection,adaptive Metropolis,delayed rejection adaptive Metropolis,Hamiltonian Monte Carlo,Hybrid Monte Carlo,HMC
Classifier: Intended Audience :: Science/Research
Classifier: License :: OSI Approved :: GNU General Public License v3 (GPLv3)
Classifier: Natural Language :: English
Classifier: Operating System :: OS Independent
Classifier: Programming Language :: Python :: 3
Classifier: Topic :: Scientific/Engineering :: Mathematics
License-File: LICENSE
Requires-Dist: torch
Dynamic: license-file
